pyuu/proxy/__init__.py
pyuu/proxy/object_proxy.py
pyuu/proxy/util.py
pyuu.proxy-0.0.2.dist-info/METADATA
pyuu.proxy-0.0.2.dist-info/WHEEL
pyuu.proxy-0.0.2.dist-info/top_level.txt
pyuu.proxy-0.0.2.dist-info/RECORD
